insidapy/__init__.py
insidapy/augment/__init__.py
insidapy/augment/mimic.py
insidapy/simulate/__init__.py
insidapy/simulate/multivariate.py
insidapy/simulate/ode.py
insidapy/simulate/univariate.py
insidapy/simulate/utils/__init__.py
insidapy/simulate/utils/ode_collection.py
insidapy/simulate/utils/ode_default_library_description.py
insidapy/simulate/utils/ode_default_settings.py
insidapy/simulate/utils/ode_default_solve_call.py
insidapy/testdata/__init__.py
insidapy/testdata/datagen.py
insidapy-0.2.10.dist-info/licenses/LICENSE
insidapy-0.2.10.dist-info/METADATA
insidapy-0.2.10.dist-info/WHEEL
insidapy-0.2.10.dist-info/top_level.txt
insidapy-0.2.10.dist-info/RECORD
