Metadata-Version: 2.4
Name: insidapy
Version: 0.2.10
Summary: Module for in-silico data generation in python.
Author: Tim Forster
License: MIT
Project-URL: Homepage, https://github.com/forstertim/insidapy
Project-URL: Documentation, https://insidapy.readthedocs.io/en/latest/?badge=latest
Project-URL: Issues, https://github.com/forstertim/insidapy/issues
License-File: LICENSE
Requires-Dist: numpy
Requires-Dist: scipy
Requires-Dist: openpyxl
Requires-Dist: matplotlib
Requires-Dist: scikit-learn
Requires-Dist: prettytable
Dynamic: author
Dynamic: description
Dynamic: description-content-type
Dynamic: license
Dynamic: license-file
Dynamic: project-url
Dynamic: requires-dist
Dynamic: summary
